COPYING
MANIFEST.in
README.md
pyproject.toml
setup.cfg
setup.py
bin/snapcraftctl
debian/changelog
extensions/desktop/LICENSE
extensions/desktop/common/desktop-exports
extensions/desktop/common/fonts
extensions/desktop/common/init
extensions/desktop/common/mark-and-exec
extensions/desktop/gnome/Makefile
extensions/desktop/gnome/desktop-exports
extensions/desktop/gnome/fonts
extensions/desktop/gnome/init
extensions/desktop/gnome/launcher-specific
extensions/desktop/gnome/mark-and-exec
extensions/desktop/kde-neon/Makefile
extensions/desktop/kde-neon/desktop-exports
extensions/desktop/kde-neon/fonts
extensions/desktop/kde-neon/init
extensions/desktop/kde-neon/launcher-specific
extensions/desktop/kde-neon/locale-gen
extensions/desktop/kde-neon/mark-and-exec
extensions/desktop/src/bindtextdomain.c
extensions/ros1/launch
extensions/ros2/launch
keyrings/ros.gpg
schema/snapcraft.json
snapcraft/__init__.py
snapcraft/_legacy_loader.py
snapcraft/_store.py
snapcraft/common.py
snapcraft/config.py
snapcraft/file_utils.py
snapcraft/formatting_utils.py
snapcraft/shell_utils.py
snapcraft/sources.py
snapcraft.egg-info/PKG-INFO
snapcraft.egg-info/SOURCES.txt
snapcraft.egg-info/dependency_links.txt
snapcraft.egg-info/entry_points.txt
snapcraft.egg-info/requires.txt
snapcraft.egg-info/top_level.txt
snapcraft/cli/__init__.py
snapcraft/cli/__main__.py
snapcraft/cli/_channel_map.py
snapcraft/cli/_command.py
snapcraft/cli/_command_group.py
snapcraft/cli/_errors.py
snapcraft/cli/_options.py
snapcraft/cli/_review.py
snapcraft/cli/_runner.py
snapcraft/cli/assertions.py
snapcraft/cli/containers.py
snapcraft/cli/discovery.py
snapcraft/cli/echo.py
snapcraft/cli/extensions.py
snapcraft/cli/help.py
snapcraft/cli/legacy.py
snapcraft/cli/lifecycle.py
snapcraft/cli/remote.py
snapcraft/cli/store.py
snapcraft/cli/version.py
snapcraft/cli/snapcraftctl/__init__.py
snapcraft/cli/snapcraftctl/_runner.py
snapcraft/extractors/__init__.py
snapcraft/extractors/_errors.py
snapcraft/extractors/_metadata.py
snapcraft/extractors/appstream.py
snapcraft/extractors/setuppy.py
snapcraft/internal/__init__.py
snapcraft/internal/common.py
snapcraft/internal/deprecations.py
snapcraft/internal/dirs.py
