Metadata-Version: 2.1
Name: snapcraft
Version: 4.8.1
Summary: Publish your app for Linux users for desktop, cloud, and IoT.
Home-page: https://github.com/snapcore/snapcraft
Author-email: snapcraft@lists.snapcraft.io
License: GPL v3
Platform: UNKNOWN
Classifier: Development Status :: 4 - Beta
Classifier: Environment :: Console
Classifier: Intended Audience :: Developers
Classifier: Intended Audience :: System Administrators
Classifier: License :: OSI Approved :: GNU General Public License v3 (GPLv3)
Classifier: Natural Language :: English
Classifier: Programming Language :: Python
Classifier: Programming Language :: Python :: 3
Classifier: Programming Language :: Python :: 3.5
Classifier: Topic :: Software Development :: Build Tools
Classifier: Topic :: System :: Software Distribution
Provides-Extra: dev
